ospgrid/__init__.py
ospgrid/grid.py
ospgrid/post.py
ospgrid/utils.py
ospgrid-0.5.3.dist-info/LICENSE
ospgrid-0.5.3.dist-info/METADATA
ospgrid-0.5.3.dist-info/WHEEL
ospgrid-0.5.3.dist-info/top_level.txt
ospgrid-0.5.3.dist-info/RECORD
