Metadata-Version: 2.1
Name: ospgrid
Version: 0.5.3
Summary: 2D grid analysis wrapper for OpenSeesPy
Author-email: Colin Caprani <colin.caprani@monash.edu>
License: GNU General Public License v3.0
Project-URL: Homepage, https://ccaprani.github.io/ospgrid/
Project-URL: Documentation, https://ccaprani.github.io/ospgrid/
Project-URL: Source, https://github.com/ccaprani/ospgrid/
Project-URL: Tracker, https://github.com/ccaprani/ospgrid/issues/
Keywords: grid,finite element,bridge
Platform: any
Classifier: Development Status :: 4 - Beta
Classifier: Topic :: Scientific/Engineering
Classifier: Environment :: Console
Classifier: Intended Audience :: Science/Research
Classifier: Programming Language :: Python :: 3 :: Only
Classifier: License :: OSI Approved :: GNU General Public License v3 (GPLv3)
Classifier: Natural Language :: English
Classifier: Operating System :: POSIX :: Linux
Classifier: Operating System :: MacOS :: MacOS X
Classifier: Operating System :: Microsoft :: Windows
Classifier: Programming Language :: Python :: 3.8
Classifier: Programming Language :: Python :: 3.9
Classifier: Programming Language :: Python :: 3.10
Classifier: Programming Language :: Python :: 3.11
Requires-Python: >=3.8
License-File: LICENSE
Requires-Dist: matplotlib
Requires-Dist: numpy
Requires-Dist: openseespy >=3.3
Requires-Dist: opsvis >=1.0.12
Provides-Extra: test
Requires-Dist: pytest >=6.2.2 ; extra == 'test'
